pyscriptlib/__init__.py
pyscriptlib/example_script.py
pyscriptlib/utils.py
pyscriptlib-2.3.1.dist-info/LICENSE
pyscriptlib-2.3.1.dist-info/METADATA
pyscriptlib-2.3.1.dist-info/WHEEL
pyscriptlib-2.3.1.dist-info/top_level.txt
pyscriptlib-2.3.1.dist-info/RECORD
