Metadata-Version: 2.1
Name: pyscriptlib
Version: 2.3.1
Summary: Python Bash Script Helpers
Home-page: https://gitlab.com/ntwrick/pyscriptlib
Author: Rick Arnold
Author-email: ntwrick@gmail.com
Keywords: scripting,shell,bash,helpers,subprocess,sys,os
Classifier: Programming Language :: Python :: 3
Classifier: License :: OSI Approved :: MIT License
Classifier: Operating System :: OS Independent
Requires-Python: >=3.6
License-File: LICENSE
